[
  {
    "Diagnosis": 3,
    "Comment": "Write a comment...",
    "DoctorId": 1,
    "Image1Id": 1,
    "Image1Name": "E:\\OneDrive - ADA University\\Homework\\SDP2022-brstcancer\\Augmentation\\Original\\image_000.jpg",
    "Rect1X1": 1727,
    "Rect1X2": 1826,
    "Rect1Y1": 1320,
    "Rect1Y2": 1540,
    "Image2Id": 2,
    "Image2Name": "E:\\OneDrive - ADA University\\Homework\\SDP2022-brstcancer\\Augmentation\\Original\\image_001.jpg",
    "Rect2X1": 1716,
    "Rect2X2": 1980,
    "Rect2Y1": 1144,
    "Rect2Y2": 1606,
    "Image3Id": 3,
    "Image3Name": "E:\\OneDrive - ADA University\\Homework\\SDP2022-brstcancer\\Augmentation\\Original\\image_002.jpg",
    "Rect3X1": 1287,
    "Rect3X2": 1606,
    "Rect3Y1": 1430,
    "Rect3Y2": 2079,
    "Image4Id": 4,
    "Image4Name": "E:\\OneDrive - ADA University\\Homework\\SDP2022-brstcancer\\Augmentation\\Original\\image_003.jpg",
    "Rect4X1": 495,
    "Rect4X2": 1056,
    "Rect4Y1": 1320,
    "Rect4Y2": 2079
  },
  {
    "Diagnosis": 1,
    "Comment": "",
    "DoctorId": 1,
    "Image1Id": 5,
    "Image1Name": "E:\\OneDrive - ADA University\\Homework\\SDP2022-brstcancer\\Augmentation\\Original\\image_004.jpg",
    "Rect1X1": 1804,
    "Rect1X2": 1936,
    "Rect1Y1": 1705,
    "Rect1Y2": 1848,
    "Image2Id": 6,
    "Image2Name": "E:\\OneDrive - ADA University\\Homework\\SDP2022-brstcancer\\Augmentation\\Original\\image_005.jpg",
    "Rect2X1": 1650,
    "Rect2X2": 1936,
    "Rect2Y1": 1485,
    "Rect2Y2": 1914,
    "Image3Id": 7,
    "Image3Name": "E:\\OneDrive - ADA University\\Homework\\SDP2022-brstcancer\\Augmentation\\Original\\image_006.jpg",
    "Rect3X1": 825,
    "Rect3X2": 1397,
    "Rect3Y1": 2057,
    "Rect3Y2": 2508,
    "Image4Id": 8,
    "Image4Name": "E:\\OneDrive - ADA University\\Homework\\SDP2022-brstcancer\\Augmentation\\Original\\image_007.jpg",
    "Rect4X1": 693,
    "Rect4X2": 1155,
    "Rect4Y1": 1749,
    "Rect4Y2": 2189
  }
]